fastrpc/__init__.py
fastrpc/file_handler.py
fastrpc/todo.py
page/__init__.py
page/file_handler.py
page/todo.py
pytodos/__init__.py
pytodos/file_handler.py
pytodos/todo.py
rapidrpc/__init__.py
rapidrpc/file_handler.py
rapidrpc/todo.py
rapidrpc-1.0.16.dist-info/DESCRIPTION.rst
rapidrpc-1.0.16.dist-info/METADATA
rapidrpc-1.0.16.dist-info/RECORD
rapidrpc-1.0.16.dist-info/WHEEL
rapidrpc-1.0.16.dist-info/entry_points.txt
rapidrpc-1.0.16.dist-info/metadata.json
rapidrpc-1.0.16.dist-info/top_level.txt
